MANIFEST.in
README.txt
setup.cfg
setup.py
docs/HISTORY.txt
docs/INSTALL.txt
docs/LICENSE.GPL
docs/LICENSE.txt
docs/Makefile
docs/conf.py
docs/index.rst
docs/make.bat
docs/resources/css3theme.jpg
redomino/__init__.py
redomino/__init__.pyc
redomino.css3theme.egg-info/PKG-INFO
redomino.css3theme.egg-info/SOURCES.txt
redomino.css3theme.egg-info/dependency_links.txt
redomino.css3theme.egg-info/entry_points.txt
redomino.css3theme.egg-info/namespace_packages.txt
redomino.css3theme.egg-info/not-zip-safe
redomino.css3theme.egg-info/requires.txt
redomino.css3theme.egg-info/top_level.txt
redomino/css3theme/__init__.py
redomino/css3theme/configure.zcml
redomino/css3theme/profiles.zcml
redomino/css3theme/setuphandlers.py
redomino/css3theme/skins.zcml
redomino/css3theme/tests.py
redomino/css3theme/version.txt
redomino/css3theme/browser/__init__.py
redomino/css3theme/browser/configure.zcml
redomino/css3theme/browser/interfaces.py
redomino/css3theme/browser/layout.py
redomino/css3theme/browser/userbodyclass.py
redomino/css3theme/browser/utility.py
redomino/css3theme/browser/resources/jquery.decomment.js
redomino/css3theme/browser/resources/jquery.mobiletable.js
redomino/css3theme/browser/resources/modernizr.min.js
redomino/css3theme/browser/resources/scrollTop.js
redomino/css3theme/browser/resources/tabbed_column.js
redomino/css3theme/browser/resources/test/jquery.mobiletable.css
redomino/css3theme/browser/resources/test/test.html
redomino/css3theme/locales/README.txt
redomino/css3theme/profiles/default/cssregistry.xml
redomino/css3theme/profiles/default/jsregistry.xml
redomino/css3theme/profiles/default/metadata.xml
redomino/css3theme/profiles/default/redomino.css3theme_various.txt
redomino/css3theme/profiles/default/registry.xml
redomino/css3theme/profiles/default/skins.xml
redomino/css3theme/profiles/default/tinymce.xml
redomino/css3theme/profiles/default/viewlets.xml
redomino/css3theme/skins/redomino_css3theme/apple-touch-icon-high.png
redomino/css3theme/skins/redomino_css3theme/apple-touch-icon-low.png
redomino/css3theme/skins/redomino_css3theme/apple-touch-icon-medium.png
redomino/css3theme/skins/redomino_css3theme/apple-touch-icon-precomposed-low.png
redomino/css3theme/skins/redomino_css3theme/column_content.png
redomino/css3theme/skins/redomino_css3theme/css3theme_all.css
