Metadata-Version: 1.0
Name: redomino.css3theme
Version: 1.5.10
Summary: A responsive (and mobile) theme for Plone 4 (based on sunburst)
Home-page: https://github.com/redomino/redomino.css3theme
Author: Maurizio Lupo
Author-email: maurizio.lupo@redomino.com
License: GPL
Keywords: Plone Theme responsive html5
Platform: UNKNOWN
Classifier: Framework :: Plone
Classifier: Programming Language :: Python
Classifier: License :: OSI Approved :: GNU General Public License (GPL)
